[
  {
    "pageid": 15739,
    "title": "N Summons List",
    "lastrevid": 409527
  },
  {
    "pageid": 13194,
    "title": "R Summons List",
    "lastrevid": 176302
  },
  {
    "pageid": 15687,
    "title": "SR Summons List",
    "lastrevid": 282258
  },
  {
    "pageid": 4087,
    "title": "SSR Summons List",
    "lastrevid": 458960
  },
  {
    "pageid": 33415,
    "title": "Adramelech",
    "lastrevid": 478761
  },
  {
    "pageid": 18537,
    "title": "Agni",
    "lastrevid": 478762
  },
  {
    "pageid": 16133,
    "title": "Air Devil",
    "lastrevid": 246270
  },
  {
    "pageid": 17213,
    "title": "Albacore",
    "lastrevid": 478763
  },
  {
    "pageid": 16200,
    "title": "Allosaurus",
    "lastrevid": 478764
  },
  {
    "pageid": 16140,
    "title": "Alpha Wolf",
    "lastrevid": 433118
  },
  {
    "pageid": 21753,
    "title": "Amber Carbuncle",
    "lastrevid": 391385
  },
  {
    "pageid": 16075,
    "title": "Anat",
    "lastrevid": 478765
  },
  {
    "pageid": 59570,
    "title": "Anat, for Love and War",
    "lastrevid": 478766
  },
  {
    "pageid": 16082,
    "title": "Angel Queen",
    "lastrevid": 402674
  },
  {
    "pageid": 25789,
    "title": "Angelie",
    "lastrevid": 433086
  },
  {
    "pageid": 21743,
    "title": "Angelie Cascade",
    "lastrevid": 318803
  },
  {
    "pageid": 31173,
    "title": "Ankusha",
    "lastrevid": 478767
  },
  {
    "pageid": 16252,
    "title": "Anneliefe",
    "lastrevid": 433066
  },
  {
    "pageid": 17408,
    "title": "Anubis",
    "lastrevid": 479224
  },
  {
    "pageid": 21632,
    "title": "Aphrodite",
    "lastrevid": 478769
  },
  {
    "pageid": 3366,
    "title": "Apollo",
    "lastrevid": 483869
  },
  {
    "pageid": 12549,
    "title": "Aquamarine Carbuncle",
    "lastrevid": 435141
  },
  {
    "pageid": 148356,
    "title": "Arbiter of Lies",
    "lastrevid": 478771
  },
  {
    "pageid": 16084,
    "title": "Archangel Queen",
    "lastrevid": 402672
  },
  {
    "pageid": 132575,
    "title": "Artemis",
    "lastrevid": 478772
  },
  {
    "pageid": 125491,
    "title": "Athena (Summer)",
    "lastrevid": 478773
  },
  {
    "pageid": 15665,
    "title": "Athena (Summon)",
    "lastrevid": 478774
  },
  {
    "pageid": 17208,
    "title": "Audumbla",
    "lastrevid": 478775
  },
  {
    "pageid": 143078,
    "title": "Automagod Triumvirate",
    "lastrevid": 478628
  },
  {
    "pageid": 18581,
    "title": "Avaritia",
    "lastrevid": 478776
  },
  {
    "pageid": 17238,
    "title": "Baal (Summon)",
    "lastrevid": 478777
  },
  {
    "pageid": 15669,
    "title": "Bahamut",
    "lastrevid": 478778
  },
  {
    "pageid": 17228,
    "title": "Bahamut Unchained",
    "lastrevid": 478779
  },
  {
    "pageid": 131410,
    "title": "Baihu",
    "lastrevid": 478780
  },
  {
    "pageid": 21049,
    "title": "Basilisk",
    "lastrevid": 433113
  },
  {
    "pageid": 111564,
    "title": "Beelzebub",
    "lastrevid": 478781
  },
  {
    "pageid": 17212,
    "title": "Behemoth",
    "lastrevid": 478782
  },
  {
    "pageid": 109613,
    "title": "Belial",
    "lastrevid": 478757
  },
  {
    "pageid": 167627,
    "title": "Belial (Summer)",
    "lastrevid": 478760
  },
  {
    "pageid": 25806,
    "title": "Belle",
    "lastrevid": 433110
  },
  {
    "pageid": 17404,
    "title": "Belle Sylphid",
    "lastrevid": 474432
  },
  {
    "pageid": 16921,
    "title": "Bellringer Angel",
    "lastrevid": 478783
  },
  {
    "pageid": 23162,
    "title": "Black Rabbit",
    "lastrevid": 439671
  },
  {
    "pageid": 132771,
    "title": "Blessed Wedding",
    "lastrevid": 478784
  },
  {
    "pageid": 15573,
    "title": "Blue Orbit",
    "lastrevid": 478785
  },
  {
    "pageid": 25803,
    "title": "Bonethorn",
    "lastrevid": 433093
  },
  {
    "pageid": 17204,
    "title": "Bonito",
    "lastrevid": 478786
  },
  {
    "pageid": 21186,
    "title": "Branwen",
    "lastrevid": 478787
  },
  {
    "pageid": 3435,
    "title": "Brunnhilde",
    "lastrevid": 478788
  },
  {
    "pageid": 96997,
    "title": "C.C.",
    "lastrevid": 478789
  },
  {
    "pageid": 17407,
    "title": "Ca Ong",
    "lastrevid": 479225
  },
  {
    "pageid": 17225,
    "title": "Cait Sith",
    "lastrevid": 478791
  },
  {
    "pageid": 20816,
    "title": "Canna",
    "lastrevid": 478792
  },
  {
    "pageid": 84974,
    "title": "Cat Parade",
    "lastrevid": 478793
  },
  {
    "pageid": 25795,
    "title": "Cave Bat",
    "lastrevid": 433104
  },
  {
    "pageid": 13201,
    "title": "Celeste",
    "lastrevid": 433111
  },
  {
    "pageid": 21750,
    "title": "Celeste Alter",
    "lastrevid": 362293
  },
  {
    "pageid": 12003,
    "title": "Celeste Omega",
    "lastrevid": 478794
  },
  {
    "pageid": 14508,
    "title": "Cerberus (Summon)",
    "lastrevid": 478795
  },
  {
    "pageid": 83848,
    "title": "Cerberus, Hellhound Trifecta",
    "lastrevid": 478796
  },
  {
    "pageid": 118344,
    "title": "Charybdis",
    "lastrevid": 478797
  },
  {
    "pageid": 17172,
    "title": "Clay Golem",
    "lastrevid": 433075
  },
  {
    "pageid": 11413,
    "title": "Cocytus",
    "lastrevid": 478798
  },
  {
    "pageid": 128314,
    "title": "Colossal Hermit",
    "lastrevid": 478799
  },
  {
    "pageid": 13198,
    "title": "Colossus (Summon)",
    "lastrevid": 391422
  },
  {
    "pageid": 21746,
    "title": "Colossus Alter",
    "lastrevid": 362288
  },
  {
    "pageid": 11996,
    "title": "Colossus Omega",
    "lastrevid": 478800
  },
  {
    "pageid": 11419,
    "title": "Corow",
    "lastrevid": 478801
  },
  {
    "pageid": 25808,
    "title": "Crawler",
    "lastrevid": 433097
  },
  {
    "pageid": 36525,
    "title": "Crimson Spear, Ebony Scythe",
    "lastrevid": 478802
  },
  {
    "pageid": 25746,
    "title": "Crusher",
    "lastrevid": 433087
  },
  {
    "pageid": 17214,
    "title": "Custos Citrullus",
    "lastrevid": 478803
  },
  {
    "pageid": 136156,
    "title": "Cutest Golden Statue in the Skies",
    "lastrevid": 483942
  },
  {
    "pageid": 17198,
    "title": "Cybele",
    "lastrevid": 478805
  },
  {
    "pageid": 102964,
    "title": "Dancing Man",
    "lastrevid": 478806
  },
  {
    "pageid": 15670,
    "title": "Dark Angel Olivia",
    "lastrevid": 478807
  },
  {
    "pageid": 17358,
    "title": "Dark Flame Scion",
    "lastrevid": 478808
  },
  {
    "pageid": 33307,
    "title": "Death (SR)",
    "lastrevid": 478809
  },
  {
    "pageid": 33368,
    "title": "Death (SSR)",
    "lastrevid": 478753
  },
  {
    "pageid": 125370,
    "title": "Deepflight Oyster",
    "lastrevid": 478810
  },
  {
    "pageid": 20556,
    "title": "Deirdre",
    "lastrevid": 478811
  },
  {
    "pageid": 89278,
    "title": "Delinquent Spirit",
    "lastrevid": 478812
  },
  {
    "pageid": 47487,
    "title": "Demi Agni",
    "lastrevid": 478813
  },
  {
    "pageid": 47494,
    "title": "Demi Hades",
    "lastrevid": 478814
  },
  {
    "pageid": 47489,
    "title": "Demi Titan",
    "lastrevid": 478815
  },
  {
    "pageid": 47488,
    "title": "Demi Varuna",
    "lastrevid": 478816
  },
  {
    "pageid": 47492,
    "title": "Demi Zephyrus",
    "lastrevid": 478817
  },
  {
    "pageid": 47493,
    "title": "Demi Zeus",
    "lastrevid": 478818
  },
  {
    "pageid": 89269,
    "title": "Demonbream",
    "lastrevid": 478819
  },
  {
    "pageid": 149383,
    "title": "Destiny Nocturnes",
    "lastrevid": 478820
  },
  {
    "pageid": 3563,
    "title": "Diablo",
    "lastrevid": 478821
  },
  {
    "pageid": 20813,
    "title": "Diantha (Summon)",
    "lastrevid": 478822
  },
  {
    "pageid": 20817,
    "title": "Diola",
    "lastrevid": 478823
  },
  {
    "pageid": 105795,
    "title": "Dogu",
    "lastrevid": 478824
  },
  {
    "pageid": 21729,
    "title": "Doomworm",
    "lastrevid": 315183
  },
  {
    "pageid": 14386,
    "title": "Dragon Knights",
    "lastrevid": 478825
  },
  {
    "pageid": 86611,
    "title": "Dragon's Rage",
    "lastrevid": 435205
  },
  {
    "pageid": 16149,
    "title": "Dragonflair",
    "lastrevid": 433100
  },
  {
    "pageid": 17223,
    "title": "Druj",
    "lastrevid": 478826
  },
  {
    "pageid": 115400,
    "title": "Dynamic Merc Duo",
    "lastrevid": 478827
  },
  {
    "pageid": 25794,
    "title": "Earth Elemental",
    "lastrevid": 433119
  },
  {
    "pageid": 17215,
    "title": "Ebisu",
    "lastrevid": 478828
  },
  {
    "pageid": 56148,
    "title": "Electric Eal",
    "lastrevid": 478829
  },
  {
    "pageid": 107422,
    "title": "Elil",
    "lastrevid": 478830
  },
  {
    "pageid": 21733,
    "title": "Elmenhilde Windsprite",
    "lastrevid": 433078
  },
  {
    "pageid": 21742,
    "title": "Elusious Windwyrm",
    "lastrevid": 433079
  },
  {
    "pageid": 34418,
    "title": "Eren",
    "lastrevid": 478831
  },
  {
    "pageid": 28381,
    "title": "Europa (Summon)",
    "lastrevid": 478832
  },
  {
    "pageid": 114674,
    "title": "Ewiyar (Summon)",
    "lastrevid": 478833
  },
  {
    "pageid": 17221,
    "title": "Fafnir",
    "lastrevid": 478834
  },
  {
    "pageid": 18504,
    "title": "Fenrir",
    "lastrevid": 478835
  },
  {
    "pageid": 25792,
    "title": "Fire Elemental",
    "lastrevid": 433114
  },
  {
    "pageid": 83242,
    "title": "Flamek Pact",
    "lastrevid": 478836
  },
  {
    "pageid": 25960,
    "title": "Forest Ranger",
    "lastrevid": 478837
  },
  {
    "pageid": 50118,
    "title": "Freyr (Summon)",
    "lastrevid": 478838
  },
  {
    "pageid": 128610,
    "title": "Freyr (Yukata)",
    "lastrevid": 478839
  },
  {
    "pageid": 95535,
    "title": "From Ladiva with Love",
    "lastrevid": 478840
  },
  {
    "pageid": 135049,
    "title": "Frost Lord's Army",
    "lastrevid": 478841
  },
  {
    "pageid": 83193,
    "title": "Gabriel",
    "lastrevid": 478842
  },
  {
    "pageid": 116438,
    "title": "Galleon (Summon)",
    "lastrevid": 478843
  },
  {
    "pageid": 12548,
    "title": "Garnet Carbuncle",
    "lastrevid": 435143
  },
  {
    "pageid": 21053,
    "title": "Garuda",
    "lastrevid": 478844
  },
  {
    "pageid": 25952,
    "title": "Garula, Shining Hawk",
    "lastrevid": 478845
  },
  {
    "pageid": 58329,
    "title": "Gearcycle",
    "lastrevid": 478846
  },
  {
    "pageid": 25807,
    "title": "Ghost Light",
    "lastrevid": 433103
  },
  {
    "pageid": 50089,
    "title": "Gigante Blazer",
    "lastrevid": 478847
  },
  {
    "pageid": 17240,
    "title": "Gilgamesh",
    "lastrevid": 478848
  },
  {
    "pageid": 138420,
    "title": "Giyu Tomioka",
    "lastrevid": 483941
  },
  {
    "pageid": 16135,
    "title": "Goblin",
    "lastrevid": 246272
  },
  {
    "pageid": 99567,
    "title": "God Albacore",
    "lastrevid": 478850
  },
  {
    "pageid": 18345,
    "title": "Godsworn Alexiel",
    "lastrevid": 478851
  },
  {
    "pageid": 159986,
    "title": "Gold Ship and Mejiro McQueen",
    "lastrevid": 483937
  },
  {
    "pageid": 119053,
    "title": "Golden Pi\u00f1a",
    "lastrevid": 478853
  },
  {
    "pageid": 21724,
    "title": "Golem",
    "lastrevid": 325804
  },
  {
    "pageid": 120453,
    "title": "Goregrinders",
    "lastrevid": 478854
  },
  {
    "pageid": 92612,
    "title": "Gorgon Sisters",
    "lastrevid": 478855
  },
  {
    "pageid": 53787,
    "title": "Gorilla",
    "lastrevid": 478856
  },
  {
    "pageid": 16627,
    "title": "Grand Order",
    "lastrevid": 478857
  },
  {
    "pageid": 20043,
    "title": "Grani",
    "lastrevid": 478858
  },
  {
    "pageid": 17207,
    "title": "Grendel",
    "lastrevid": 478859
  },
  {
    "pageid": 13203,
    "title": "Griffin",
    "lastrevid": 433080
  },
  {
    "pageid": 36516,
    "title": "Grimnir (Summon)",
    "lastrevid": 478860
  },
  {
    "pageid": 3709,
    "title": "Grueler",
    "lastrevid": 478861
  },
  {
    "pageid": 137185,
    "title": "Guardian Ku-Keoloewa",
    "lastrevid": 483943
  },
  {
    "pageid": 17210,
    "title": "Gugalanna",
    "lastrevid": 478863
  },
  {
    "pageid": 59577,
    "title": "H.D. Mining Excavator",
    "lastrevid": 478864
  },
  {
    "pageid": 18413,
    "title": "H.P.A.",
    "lastrevid": 478865
  },
  {
    "pageid": 15667,
    "title": "Hades",
    "lastrevid": 478759
  },
  {
    "pageid": 47452,
    "title": "Halluel and Malluel",
    "lastrevid": 478866
  },
  {
    "pageid": 58333,
    "title": "Hamsa",
    "lastrevid": 478867
  },
  {
    "pageid": 20815,
    "title": "Harie",
    "lastrevid": 478868
  },
  {
    "pageid": 20640,
    "title": "Harvest Myconid",
    "lastrevid": 478869
  },
  {
    "pageid": 17313,
    "title": "Hector",
    "lastrevid": 479223
  },
  {
    "pageid": 111343,
    "title": "Heimdallr",
    "lastrevid": 478871
  },
  {
    "pageid": 169688,
    "title": "Hekate",
    "lastrevid": 482425
  },
  {
    "pageid": 20636,
    "title": "Hekatonkheir",
    "lastrevid": 478872
  },
  {
    "pageid": 21728,
    "title": "Hellhound",
    "lastrevid": 325732
  },
  {
    "pageid": 21731,
    "title": "Hitodama",
    "lastrevid": 341394
  },
  {
    "pageid": 16144,
    "title": "Hornbird",
    "lastrevid": 433101
  },
  {
    "pageid": 16626,
    "title": "Huanglong",
    "lastrevid": 478758
  },
  {
    "pageid": 21725,
    "title": "Hydra",
    "lastrevid": 433073
  },
  {
    "pageid": 141830,
    "title": "Idle Sparkle",
    "lastrevid": 478873
  },
  {
    "pageid": 11411,
    "title": "Ifrit",
    "lastrevid": 478874
  },
  {
    "pageid": 133707,
    "title": "Ignis Dragon",
    "lastrevid": 478875
  },
  {
    "pageid": 21052,
    "title": "Ikelos",
    "lastrevid": 478876
  },
  {
    "pageid": 17226,
    "title": "Illuyanka",
    "lastrevid": 478877
  },
  {
    "pageid": 25802,
    "title": "Imp",
    "lastrevid": 433105
  },
  {
    "pageid": 21047,
    "title": "Inchoate World",
    "lastrevid": 478878
  },
  {
    "pageid": 3768,
    "title": "Jack-o'-Lantern",
    "lastrevid": 478879
  },
  {
    "pageid": 21754,
    "title": "Jade Carbuncle",
    "lastrevid": 391386
  },
  {
    "pageid": 25790,
    "title": "Jawfish",
    "lastrevid": 433088
  },
  {
    "pageid": 57702,
    "title": "JEHUTY",
    "lastrevid": 478880
  },
  {
    "pageid": 37746,
    "title": "Joya",
    "lastrevid": 478881
  },
  {
    "pageid": 33335,
    "title": "Judgement (SR)",
    "lastrevid": 478882
  },
  {
    "pageid": 33375,
    "title": "Judgement (SSR)",
    "lastrevid": 478883
  },
  {
    "pageid": 33304,
    "title": "Justice (SR)",
    "lastrevid": 478884
  },
  {
    "pageid": 33366,
    "title": "Justice (SSR)",
    "lastrevid": 478885
  },
  {
    "pageid": 17202,
    "title": "Kaguya",
    "lastrevid": 478886
  },
  {
    "pageid": 129998,
    "title": "Kaguya (Summer)",
    "lastrevid": 478887
  },
  {
    "pageid": 31630,
    "title": "Kero-chan",
    "lastrevid": 478888
  },
  {
    "pageid": 16134,
    "title": "Killer Bee",
    "lastrevid": 325782
  },
  {
    "pageid": 21050,
    "title": "King Krustacea",
    "lastrevid": 478889
  },
  {
    "pageid": 17224,
    "title": "Kirari",
    "lastrevid": 478890
  },
  {
    "pageid": 17220,
    "title": "Kirari Moroboshi",
    "lastrevid": 478891
  },
  {
    "pageid": 33431,
    "title": "Knight of Knights",
    "lastrevid": 478892
  },
  {
    "pageid": 154916,
    "title": "Kotaro Katsura and Elizabeth",
    "lastrevid": 478893
  },
  {
    "pageid": 70206,
    "title": "Krelkulkil",
    "lastrevid": 478894
  },
  {
    "pageid": 17376,
    "title": "Lady Katapillar",
    "lastrevid": 478895
  },
  {
    "pageid": 16146,
    "title": "Lavavian",
    "lastrevid": 433115
  },
  {
    "pageid": 13199,
    "title": "Leviathan",
    "lastrevid": 404758
  },
  {
    "pageid": 21747,
    "title": "Leviathan Alter",
    "lastrevid": 362289
  },
  {
    "pageid": 3844,
    "title": "Leviathan Omega",
    "lastrevid": 478896
  },
  {
    "pageid": 16383,
    "title": "Levin Sisters (Summon)",
    "lastrevid": 478752
  },
  {
    "pageid": 18538,
    "title": "Lich (Summon)",
    "lastrevid": 478897
  },
  {
    "pageid": 20814,
    "title": "Linaria",
    "lastrevid": 478898
  },
  {
    "pageid": 29455,
    "title": "Lonesome Dragoness (Summon)",
    "lastrevid": 478899
  },
  {
    "pageid": 161981,
    "title": "Lu Woh (Summon)",
    "lastrevid": 478900
  },
  {
    "pageid": 15689,
    "title": "Lucifer",
    "lastrevid": 478901
  },
  {
    "pageid": 25797,
    "title": "Lumacie Griffin",
    "lastrevid": 433096
  },
  {
    "pageid": 21586,
    "title": "Lumiel Gourmet",
    "lastrevid": 478902
  },
  {
    "pageid": 13200,
    "title": "Luminiera",
    "lastrevid": 391414
  },
  {
    "pageid": 21749,
    "title": "Luminiera Alter",
    "lastrevid": 362292
  },
  {
    "pageid": 12001,
    "title": "Luminiera Omega",
    "lastrevid": 478755
  },
  {
    "pageid": 53794,
    "title": "Lunalu (Summon)",
    "lastrevid": 478903
  },
  {
    "pageid": 21730,
    "title": "Machina Soldier MK II",
    "lastrevid": 325793
  },
  {
    "pageid": 56144,
    "title": "Macula Marius (Summer)",
    "lastrevid": 478904
  },
  {
    "pageid": 16080,
    "title": "Macula Marius (Summon)",
    "lastrevid": 479876
  },
  {
    "pageid": 16145,
    "title": "Magma Golem",
    "lastrevid": 433116
  },
  {
    "pageid": 21245,
    "title": "Magus",
    "lastrevid": 478906
  },
  {
    "pageid": 84973,
    "title": "Magus, Triad of Wisdom",
    "lastrevid": 478907
  },
  {
    "pageid": 17211,
    "title": "Mahisha",
    "lastrevid": 478908
  },
  {
    "pageid": 20635,
    "title": "Mammon",
    "lastrevid": 478909
  },
  {
    "pageid": 125492,
    "title": "Mammoth",
    "lastrevid": 478910
  },
  {
    "pageid": 17218,
    "title": "Manawydan",
    "lastrevid": 478911
  },
  {
    "pageid": 16150,
    "title": "Mandrake",
    "lastrevid": 433095
  },
  {
    "pageid": 152647,
    "title": "Mandrake (Summer)",
    "lastrevid": 478912
  },
  {
    "pageid": 12142,
    "title": "Marduk",
    "lastrevid": 478913
  },
  {
    "pageid": 86948,
    "title": "Marduk, Battlefield Reaper",
    "lastrevid": 478914
  },
  {
    "pageid": 16076,
    "title": "Medusa (Summon)",
    "lastrevid": 478915
  },
  {
    "pageid": 59928,
    "title": "Mepple and Mipple",
    "lastrevid": 478916
  },
  {
    "pageid": 96136,
    "title": "Metatron",
    "lastrevid": 478917
  },
  {
    "pageid": 64231,
    "title": "Michael",
    "lastrevid": 478918
  },
  {
    "pageid": 20634,
    "title": "Midgardsormr",
    "lastrevid": 478919
  },
  {
    "pageid": 13365,
    "title": "Milia",
    "lastrevid": 478920
  },
  {
    "pageid": 25747,
    "title": "Minotaur",
    "lastrevid": 433082
  },
  {
    "pageid": 16132,
    "title": "Mirage Maker",
    "lastrevid": 425544
  },
  {
    "pageid": 13204,
    "title": "Mithra",
    "lastrevid": 478921
  },
  {
    "pageid": 21755,
    "title": "Moonlight Carbuncle",
    "lastrevid": 391387
  },
  {
    "pageid": 54632,
    "title": "Morgana Car",
    "lastrevid": 478922
  },
  {
    "pageid": 17406,
    "title": "Morrigna (Summon)",
    "lastrevid": 479222
  },
  {
    "pageid": 108098,
    "title": "Mukku",
    "lastrevid": 478924
  },
  {
    "pageid": 21727,
    "title": "Myconid",
    "lastrevid": 433076
  },
  {
    "pageid": 20062,
    "title": "Nacht",
    "lastrevid": 478925
  },
  {
    "pageid": 55228,
    "title": "Narita",
    "lastrevid": 435145
  },
  {
    "pageid": 21201,
    "title": "Nephthys",
    "lastrevid": 478926
  },
  {
    "pageid": 18539,
    "title": "Neptune",
    "lastrevid": 478927
  },
  {
    "pageid": 16081,
    "title": "Nezha (Summon)",
    "lastrevid": 478928
  },
  {
    "pageid": 55173,
    "title": "Nobiyo",
    "lastrevid": 481799
  },
  {
    "pageid": 21744,
    "title": "Nopal",
    "lastrevid": 72341
  },
  {
    "pageid": 113226,
    "title": "Nyarlathotep",
    "lastrevid": 478929
  },
  {
    "pageid": 21756,
    "title": "Obsidian Carbuncle",
    "lastrevid": 391388
  },
  {
    "pageid": 17194,
    "title": "Oceanus",
    "lastrevid": 478930
  },
  {
    "pageid": 17222,
    "title": "Odajumoki Gang",
    "lastrevid": 478931
  },
  {
    "pageid": 15764,
    "title": "Odin",
    "lastrevid": 478932
  },
  {
    "pageid": 12552,
    "title": "Onyx Carbuncle",
    "lastrevid": 435138
  },
  {
    "pageid": 12551,
    "title": "Opal Carbuncle",
    "lastrevid": 435139
  },
  {
    "pageid": 120582,
    "title": "Owlcat",
    "lastrevid": 478933
  },
  {
    "pageid": 17216,
    "title": "Oxymoron",
    "lastrevid": 478934
  },
  {
    "pageid": 12547,
    "title": "Peridot Carbuncle",
    "lastrevid": 435142
  },
  {
    "pageid": 21244,
    "title": "Phoenix",
    "lastrevid": 478935
  },
  {
    "pageid": 20992,
    "title": "Pierre",
    "lastrevid": 478936
  },
  {
    "pageid": 16137,
    "title": "Pincer",
    "lastrevid": 325780
  },
  {
    "pageid": 21741,
    "title": "Pixie",
    "lastrevid": 433081
  },
  {
    "pageid": 17219,
    "title": "Poseidon (Summon)",
    "lastrevid": 478937
  },
  {
    "pageid": 70102,
    "title": "Poseidon, the Tide Father",
    "lastrevid": 479882
  },
  {
    "pageid": 76034,
    "title": "Princess Knight",
    "lastrevid": 478939
  },
  {
    "pageid": 104545,
    "title": "Princess Long Ji",
    "lastrevid": 478940
  },
  {
    "pageid": 15666,
    "title": "Prometheus",
    "lastrevid": 478941
  },
  {
    "pageid": 13202,
    "title": "Proto Bahamut",
    "lastrevid": 391392
  },
  {
    "pageid": 109504,
    "title": "Proto-Joya",
    "lastrevid": 478942
  },
  {
    "pageid": 25805,
    "title": "Purgatorian",
    "lastrevid": 433089
  },
  {
    "pageid": 16625,
    "title": "Qilin",
    "lastrevid": 478943
  },
  {
    "pageid": 131411,
    "title": "Qinglong",
    "lastrevid": 478944
  },
  {
    "pageid": 17227,
    "title": "Queen Bee",
    "lastrevid": 478945
  },
  {
    "pageid": 17193,
    "title": "Quetzalcoatl",
    "lastrevid": 478946
  },
  {
    "pageid": 98209,
    "title": "Rainy Day",
    "lastrevid": 482670
  },
  {
    "pageid": 4024,
    "title": "Ranko Kanzaki (Summon)",
    "lastrevid": 478948
  },
  {
    "pageid": 55225,
    "title": "Raphael",
    "lastrevid": 478949
  },
  {
    "pageid": 115502,
    "title": "Red Hare",
    "lastrevid": 478950
  },
  {
    "pageid": 25796,
    "title": "Rivacuda",
    "lastrevid": 433090
  },
  {
    "pageid": 10490,
    "title": "Robomi Rocket",
    "lastrevid": 478951
  },
  {
    "pageid": 25799,
    "title": "Rodfly",
    "lastrevid": 433102
  },
  {
    "pageid": 17286,
    "title": "Rose Queen",
    "lastrevid": 478952
  },
  {
    "pageid": 101540,
    "title": "Rose Queen (Summer)",
    "lastrevid": 479088
  },
  {
    "pageid": 21751,
    "title": "Ruby Carbuncle",
    "lastrevid": 391383
  },
  {
    "pageid": 21736,
    "title": "Ruination Gargoyle",
    "lastrevid": 325788
  },
  {
    "pageid": 11417,
    "title": "Sagittarius",
    "lastrevid": 478954
  },
  {
    "pageid": 47498,
    "title": "Sandalphon (Summon)",
    "lastrevid": 478955
  },
  {
    "pageid": 21752,
    "title": "Sapphire Carbuncle",
    "lastrevid": 391384
  },
  {
    "pageid": 32215,
    "title": "Sapphire Dance: Gentiana",
    "lastrevid": 478956
  },
  {
    "pageid": 105708,
    "title": "Sapphire Dance: Habotan",
    "lastrevid": 478957
  },
  {
    "pageid": 92538,
    "title": "Sariel",
    "lastrevid": 478958
  },
  {
    "pageid": 137241,
    "title": "Sariel (Holiday)",
    "lastrevid": 478959
  },
  {
    "pageid": 17197,
    "title": "Satan",
    "lastrevid": 478960
  },
  {
    "pageid": 100031,
    "title": "Satyr (Summer)",
    "lastrevid": 478961
  },
  {
    "pageid": 17199,
    "title": "Satyr (Summon)",
    "lastrevid": 478962
  },
  {
    "pageid": 16136,
    "title": "Scalewing",
    "lastrevid": 246273
  },
  {
    "pageid": 17653,
    "title": "Seraphim Cradle",
    "lastrevid": 478963
  },
  {
    "pageid": 4130,
    "title": "Setekh",
    "lastrevid": 478964
  },
  {
    "pageid": 17203,
    "title": "Sethlans",
    "lastrevid": 478965
  },
  {
    "pageid": 164731,
    "title": "Shantotto II",
    "lastrevid": 483940
  },
  {
    "pageid": 31174,
    "title": "Sharom",
    "lastrevid": 478967
  },
  {
    "pageid": 15592,
    "title": "Shiva (Summon)",
    "lastrevid": 478968
  },
  {
    "pageid": 156323,
    "title": "Shizuka, Gian, and Suneo",
    "lastrevid": 478969
  },
  {
    "pageid": 118292,
    "title": "Silver Salvation",
    "lastrevid": 478970
  },
  {
    "pageid": 17195,
    "title": "Siren",
    "lastrevid": 478971
  },
  {
    "pageid": 16148,
    "title": "Skeleton",
    "lastrevid": 433106
  },
  {
    "pageid": 16138,
    "title": "Skewerfish",
    "lastrevid": 325783
  },
  {
    "pageid": 107326,
    "title": "Sky Carriage SS Pew Pew",
    "lastrevid": 479086
  },
  {
    "pageid": 25748,
    "title": "Sleepyhead",
    "lastrevid": 433099
  },
  {
    "pageid": 168186,
    "title": "Sleepyhead (Summer)",
    "lastrevid": 479871
  },
  {
    "pageid": 25801,
    "title": "Slime",
    "lastrevid": 433091
  },
  {
    "pageid": 145782,
    "title": "Snapshot of Divinity",
    "lastrevid": 478973
  },
  {
    "pageid": 32208,
    "title": "Snow White",
    "lastrevid": 478974
  },
  {
    "pageid": 25744,
    "title": "Spearsting",
    "lastrevid": 176306
  },
  {
    "pageid": 21735,
    "title": "Stone Golem",
    "lastrevid": 433077
  },
  {
    "pageid": 16143,
    "title": "Storm Rabbit",
    "lastrevid": 433120
  },
  {
    "pageid": 20061,
    "title": "Super Cute Genius Alchemist",
    "lastrevid": 478975
  },
  {
    "pageid": 17217,
    "title": "Super Robo Gigantes",
    "lastrevid": 478976
  },
  {
    "pageid": 103037,
    "title": "Surtr",
    "lastrevid": 478977
  },
  {
    "pageid": 110961,
    "title": "Swinger of the Ebony Scythe",
    "lastrevid": 478978
  },
  {
    "pageid": 25791,
    "title": "Swordshark",
    "lastrevid": 433092
  },
  {
    "pageid": 13851,
    "title": "Sylph (Summon)",
    "lastrevid": 478979
  },
  {
    "pageid": 82397,
    "title": "Sylph, Flutterspirit of Purity",
    "lastrevid": 478980
  },
  {
    "pageid": 104179,
    "title": "Team Chickadee",
    "lastrevid": 478981
  },
  {
    "pageid": 33308,
    "title": "Temperance (SR)",
    "lastrevid": 478982
  },
  {
    "pageid": 33369,
    "title": "Temperance (SSR)",
    "lastrevid": 478983
  },
  {
    "pageid": 17205,
    "title": "Tezcatlipoca",
    "lastrevid": 478984
  },
  {
    "pageid": 33330,
    "title": "The Devil (SR)",
    "lastrevid": 478985
  },
  {
    "pageid": 33370,
    "title": "The Devil (SSR)",
    "lastrevid": 478986
  },
  {
    "pageid": 112662,
    "title": "The Eternal Defenders",
    "lastrevid": 478987
  },
  {
    "pageid": 33306,
    "title": "The Hanged Man (SR)",
    "lastrevid": 478988
  },
  {
    "pageid": 33367,
    "title": "The Hanged Man (SSR)",
    "lastrevid": 478989
  },
  {
    "pageid": 33333,
    "title": "The Moon (SR)",
    "lastrevid": 478990
  },
  {
    "pageid": 33373,
    "title": "The Moon (SSR)",
    "lastrevid": 478991
  },
  {
    "pageid": 33332,
    "title": "The Star (SR)",
    "lastrevid": 478992
  },
  {
    "pageid": 33372,
    "title": "The Star (SSR)",
    "lastrevid": 478993
  },
  {
    "pageid": 33334,
    "title": "The Sun (SR)",
    "lastrevid": 478994
  },
  {
    "pageid": 33374,
    "title": "The Sun (SSR)",
    "lastrevid": 478995
  },
  {
    "pageid": 33331,
    "title": "The Tower (SR)",
    "lastrevid": 478996
  },
  {
    "pageid": 33371,
    "title": "The Tower (SSR)",
    "lastrevid": 478997
  },
  {
    "pageid": 16413,
    "title": "Thor",
    "lastrevid": 478998
  },
  {
    "pageid": 21051,
    "title": "Ti Icniuhtli Xolotl",
    "lastrevid": 478999
  },
  {
    "pageid": 151101,
    "title": "Tiamat (Summer)",
    "lastrevid": 479000
  },
  {
    "pageid": 13197,
    "title": "Tiamat (Summon)",
    "lastrevid": 391416
  },
  {
    "pageid": 21745,
    "title": "Tiamat Alter",
    "lastrevid": 362291
  },
  {
    "pageid": 12000,
    "title": "Tiamat Omega",
    "lastrevid": 479001
  },
  {
    "pageid": 16139,
    "title": "Timber Wolf",
    "lastrevid": 325760
  },
  {
    "pageid": 17239,
    "title": "Titan",
    "lastrevid": 478756
  },
  {
    "pageid": 13364,
    "title": "Treant",
    "lastrevid": 479002
  },
  {
    "pageid": 139991,
    "title": "Tsuchinoko",
    "lastrevid": 479003
  },
  {
    "pageid": 37721,
    "title": "Tsukuyomi",
    "lastrevid": 479004
  },
  {
    "pageid": 25804,
    "title": "Twilight Devil",
    "lastrevid": 433083
  },
  {
    "pageid": 4277,
    "title": "Twin Elements",
    "lastrevid": 479005
  },
  {
    "pageid": 17206,
    "title": "Typhon",
    "lastrevid": 479006
  },
  {
    "pageid": 139725,
    "title": "Ultra Robo Grand God Kaiser",
    "lastrevid": 479007
  },
  {
    "pageid": 51590,
    "title": "Unrivaled Fighter",
    "lastrevid": 479008
  },
  {
    "pageid": 51568,
    "title": "Uriel",
    "lastrevid": 479009
  },
  {
    "pageid": 28429,
    "title": "Urkin",
    "lastrevid": 479010
  },
  {
    "pageid": 169078,
    "title": "Usopp, Chopper, Franky, Brook, and Jimbei",
    "lastrevid": 483939
  },
  {
    "pageid": 169058,
    "title": "Uta",
    "lastrevid": 483938
  },
  {
    "pageid": 64244,
    "title": "Vane's Cooking",
    "lastrevid": 478751
  },
  {
    "pageid": 17200,
    "title": "Varuna",
    "lastrevid": 479013
  },
  {
    "pageid": 25798,
    "title": "Venom Lancer",
    "lastrevid": 433084
  },
  {
    "pageid": 4309,
    "title": "Verona Heart",
    "lastrevid": 479014
  },
  {
    "pageid": 13363,
    "title": "Veselago",
    "lastrevid": 479015
  },
  {
    "pageid": 11415,
    "title": "Vohu Manah",
    "lastrevid": 479016
  },
  {
    "pageid": 17192,
    "title": "Vortex Dragon",
    "lastrevid": 479017
  },
  {
    "pageid": 21734,
    "title": "Vrazarek Firewyrm",
    "lastrevid": 325789
  },
  {
    "pageid": 25800,
    "title": "Walking Torch",
    "lastrevid": 433085
  },
  {
    "pageid": 168758,
    "title": "Wamdus (Summon)",
    "lastrevid": 479018
  },
  {
    "pageid": 25793,
    "title": "Water Elemental",
    "lastrevid": 433117
  },
  {
    "pageid": 4340,
    "title": "White Rabbit",
    "lastrevid": 437003
  },
  {
    "pageid": 21732,
    "title": "Wilinus Icewyrm",
    "lastrevid": 433074
  },
  {
    "pageid": 114191,
    "title": "Wilnas (Summon)",
    "lastrevid": 481948
  },
  {
    "pageid": 16147,
    "title": "Wind Elemental",
    "lastrevid": 433121
  },
  {
    "pageid": 15803,
    "title": "Wind God and Thunder God",
    "lastrevid": 479020
  },
  {
    "pageid": 15688,
    "title": "Wind Rabbit",
    "lastrevid": 325777
  },
  {
    "pageid": 21726,
    "title": "Wyvern",
    "lastrevid": 325751
  },
  {
    "pageid": 143924,
    "title": "Xeno Cocytus",
    "lastrevid": 479021
  },
  {
    "pageid": 139253,
    "title": "Xeno Corow",
    "lastrevid": 479022
  },
  {
    "pageid": 148709,
    "title": "Xeno Diablo",
    "lastrevid": 479023
  },
  {
    "pageid": 124444,
    "title": "Xeno Ifrit",
    "lastrevid": 479024
  },
  {
    "pageid": 133426,
    "title": "Xeno Sagittarius",
    "lastrevid": 479025
  },
  {
    "pageid": 52500,
    "title": "Xeno Vohu Manah",
    "lastrevid": 479026
  },
  {
    "pageid": 131409,
    "title": "Xuanwu",
    "lastrevid": 479027
  },
  {
    "pageid": 98512,
    "title": "Yggdrasil (Summer)",
    "lastrevid": 479028
  },
  {
    "pageid": 13196,
    "title": "Yggdrasil (Summon)",
    "lastrevid": 392603
  },
  {
    "pageid": 21748,
    "title": "Yggdrasil Alter",
    "lastrevid": 392602
  },
  {
    "pageid": 11999,
    "title": "Yggdrasil Omega",
    "lastrevid": 478754
  },
  {
    "pageid": 29459,
    "title": "Zaoshen",
    "lastrevid": 479029
  },
  {
    "pageid": 18536,
    "title": "Zephyrus",
    "lastrevid": 479030
  },
  {
    "pageid": 17201,
    "title": "Zeus",
    "lastrevid": 479031
  },
  {
    "pageid": 131408,
    "title": "Zhuque",
    "lastrevid": 479032
  },
  {
    "pageid": 12550,
    "title": "Zircon Carbuncle",
    "lastrevid": 435140
  },
  {
    "pageid": 135142,
    "title": "Zirnitra",
    "lastrevid": 479033
  },
  {
    "pageid": 126394,
    "title": "Category:Archangel Series Summons",
    "lastrevid": 363114
  },
  {
    "pageid": 88541,
    "title": "Category:Genesis Series Summons",
    "lastrevid": 362106
  },
  {
    "pageid": 88542,
    "title": "Category:Non-Ticketable Summons",
    "lastrevid": 256008
  },
  {
    "pageid": 13195,
    "title": "Category:R Summons",
    "lastrevid": 24355
  },
  {
    "pageid": 152623,
    "title": "Category:Rise of the Beasts Summons",
    "lastrevid": 432226
  },
  {
    "pageid": 15740,
    "title": "Category:SR Summons",
    "lastrevid": 32235
  },
  {
    "pageid": 9998,
    "title": "Category:SSR Summons",
    "lastrevid": 24351
  }
]